CursoTest/__init__.py
CursoTest/core.py
cursotest_package-1.0.0.dist-info/METADATA
cursotest_package-1.0.0.dist-info/WHEEL
cursotest_package-1.0.0.dist-info/top_level.txt
cursotest_package-1.0.0.dist-info/RECORD
