Metadata-Version: 2.1
Name: cursotest-package
Version: 1.0.0
Summary: Descricao da sua lib CursoTest
Home-page: https://github.com/igorjanuario/CursoTest
Author: Igor Januario
Author-email: igorjanuariod@gmail.com
License: MIT
Platform: UNKNOWN
